psread/__init__.py
psread/psread.py
psread-0.1.2.dist-info/LICENSE
psread-0.1.2.dist-info/METADATA
psread-0.1.2.dist-info/WHEEL
psread-0.1.2.dist-info/entry_points.txt
psread-0.1.2.dist-info/top_level.txt
psread-0.1.2.dist-info/RECORD
