Metadata-Version: 2.1
Name: psread
Version: 0.1.2
Summary: Quick, simple AWS Parameter Store CLI for listing/reading params with tab completion
Home-page: https://github.com/jantman/psread
Author: Jason Antman
Author-email: jason@jasonantman.com
License: UNKNOWN
Keywords: aws parameter-store aws-parameter-store secrets
Platform: UNKNOWN
Classifier: Development Status :: 4 - Beta
Classifier: Environment :: Console
Classifier: Programming Language :: Python :: 3 :: Only
Classifier: Programming Language :: Python :: 3.6
Classifier: Programming Language :: Python :: 3.7
Classifier: Programming Language :: Python :: 3.8
Requires-Dist: boto3
Requires-Dist: argcomplete
Requires-Dist: appdirs
